technical_backtesting_mcp/__init__.py
technical_backtesting_mcp/__main__.py
technical_backtesting_mcp/py.typed
technical_backtesting_mcp/backtesters/__init__.py
technical_backtesting_mcp/backtesters/cross_moving_average.py
technical_backtesting_mcp-0.2.2.dist-info/METADATA
technical_backtesting_mcp-0.2.2.dist-info/WHEEL
technical_backtesting_mcp-0.2.2.dist-info/entry_points.txt
technical_backtesting_mcp-0.2.2.dist-info/licenses/LICENSE
technical_backtesting_mcp-0.2.2.dist-info/RECORD
