Metadata-Version: 2.4
Name: technical-backtesting-mcp
Version: 0.2.2
Summary: Add your description here
Author-email: prem <prem.ch@ku.th>
License-File: LICENSE
Requires-Python: >=3.13
Requires-Dist: backtesting>=0.6.4
Requires-Dist: click>=8.2.1
Requires-Dist: fastmcp>=2.5.2
Requires-Dist: price-loaders>=0.2.1
